README.md
setup.py
TOPSIS_Prajjwal_101803111.egg-info/PKG-INFO
TOPSIS_Prajjwal_101803111.egg-info/SOURCES.txt
TOPSIS_Prajjwal_101803111.egg-info/dependency_links.txt
TOPSIS_Prajjwal_101803111.egg-info/top_level.txt
topsis_cal/__init__.py
topsis_cal/topsiscode.py