Metadata-Version: 2.1
Name: TOPSIS-Prajjwal-101803111
Version: 1.0.1
Summary: Topsis Calculator
Home-page: UNKNOWN
Author: Prajjwal Upadhyay
Author-email: prajjwal.upadhyay.12345@gmail.com
License: UNKNOWN
Platform: UNKNOWN
Classifier: Programming Language :: Python :: 3
Classifier: License :: OSI Approved :: MIT License
Classifier: Operating System :: OS Independent
